oasm/rtmq/__init__.py
oasm/rtmq/intf.py
oasm/rtmq/rwg.py
oasm_rtmq-0.1.4.dist-info/METADATA
oasm_rtmq-0.1.4.dist-info/WHEEL
oasm_rtmq-0.1.4.dist-info/top_level.txt
oasm_rtmq-0.1.4.dist-info/RECORD
