Metadata-Version: 2.4
Name: oasm.rtmq
Version: 0.1.4
Summary: Open ASseMbly tools - RTMQ
Author-email: nzturn <nzturn@gmail.com>
Keywords: asm,dsl
Classifier: Development Status :: 3 - Alpha
Classifier: Intended Audience :: Developers
Classifier: Programming Language :: Python :: 3
Requires-Python: >=3.8
Requires-Dist: oasm
